ggui/__init__.py
ggui/__version__.py
ggui/autochop.py
ggui/config.py
ggui/ggui.conf
ggui/ggui.py
ggui/main.py
ggui/make_param.py
ggui/mastCrossSearch.py
ggui/qtTabLayouts.py
ggui/targetManager.py
ggui/version.py
ggui/icons/ArrowBack_transparent.png
ggui/icons/ArrowForward_transparent.png
ggui/icons/FUV_transparent.png
ggui/icons/Focus.png
ggui/icons/Information.svg
ggui/icons/NUV_transparent.png
ggui/icons/Notepad.png
ggui/icons/__init__.py
ggui-1.2.0.dist-info/LICENSE
ggui-1.2.0.dist-info/METADATA
ggui-1.2.0.dist-info/WHEEL
ggui-1.2.0.dist-info/entry_points.txt
ggui-1.2.0.dist-info/top_level.txt
ggui-1.2.0.dist-info/RECORD
