Metadata-Version: 2.1
Name: ggui
Version: 1.2.0
Summary: gPhoton Graphical User Interface
Home-page: https://github.com/gphoton-tools/ggui
Author: Duy Tuong Nguyen, Scott Fleming
Author-email: dnguyen@nrao.edu
License: MIT
Platform: UNKNOWN
Classifier: License :: OSI Approved :: MIT License
Classifier: Programming Language :: Python
Classifier: Programming Language :: Python :: 3
Classifier: Programming Language :: Python :: 3.6
Classifier: Programming Language :: Python :: Implementation :: CPython
Classifier: Programming Language :: Python :: Implementation :: PyPy
Requires-Python: >=3.6.0
Requires-Dist: pyqt5
Requires-Dist: glueviz (>=0.13.3)
Requires-Dist: pyyaml
